aws_a2i/__init__.py
aws_a2i/_version.py
aws_a2i/api.py
aws_a2i/helper.py
aws_a2i/playground.py
aws_a2i/tagging.py
aws_a2i/tools.py
aws_a2i/waiter.py
aws_a2i/better_boto/__init__.py
aws_a2i/better_boto/flow_definition.py
aws_a2i/better_boto/human_loop.py
aws_a2i/better_boto/human_task_ui.py
aws_a2i/docs/__init__.py
aws_a2i-0.3.1.dist-info/AUTHORS.rst
aws_a2i-0.3.1.dist-info/LICENSE.txt
aws_a2i-0.3.1.dist-info/METADATA
aws_a2i-0.3.1.dist-info/WHEEL
aws_a2i-0.3.1.dist-info/top_level.txt
aws_a2i-0.3.1.dist-info/RECORD
